swarmauri_embedding_nmf/NmfEmbedding.py
swarmauri_embedding_nmf/__init__.py
swarmauri_embedding_nmf-0.7.5.dist-info/LICENSE
swarmauri_embedding_nmf-0.7.5.dist-info/METADATA
swarmauri_embedding_nmf-0.7.5.dist-info/WHEEL
swarmauri_embedding_nmf-0.7.5.dist-info/entry_points.txt
swarmauri_embedding_nmf-0.7.5.dist-info/RECORD
